nonebot_plugin_pixivrank_search/__init__.py
nonebot_plugin_pixivrank_search/config.py
nonebot_plugin_pixivrank_search/data_source.py
nonebot_plugin_pixivrank_search/util.py
nonebot_plugin_pixivrank_search-0.6.dist-info/LICENSE
nonebot_plugin_pixivrank_search-0.6.dist-info/WHEEL
nonebot_plugin_pixivrank_search-0.6.dist-info/METADATA
nonebot_plugin_pixivrank_search-0.6.dist-info/RECORD
