Metadata-Version: 2.1
Name: nonebot-plugin-pixivrank-search
Version: 0.6
Summary: 基于RSSHUB阅读器实现的获取P站排行和P站搜图
License: MIT
Author: HibiKier
Author-email: 775757368@qq.com
Requires-Python: >=3.7.3,<4.0.0
Classifier: License :: OSI Approved :: MIT License
Classifier: Programming Language :: Python :: 3
Classifier: Programming Language :: Python :: 3.10
Classifier: Programming Language :: Python :: 3.8
Classifier: Programming Language :: Python :: 3.9
Requires-Dist: aiofiles (>=0.8.0,<0.9.0)
Requires-Dist: aiohttp (>=3.8.1,<4.0.0)
Requires-Dist: beautifulsoup4 (>=4.10.0,<5.0.0)
Requires-Dist: feedparser (>=6.0.8,<7.0.0)
Requires-Dist: lxml (>=4.7.1,<5.0.0)
Requires-Dist: nonebot-adapter-onebot (>=2.0.0-beta.1,<3.0.0)
Requires-Dist: nonebot2 (>=2.0.0-beta.2,<3.0.0)
